{"cameraMode":{"drawMode":0,"name":"Shaded","section":"Shading Mode"},"sceneLighting":false,"audioPlay":false,"sceneViewState":{"showFog":true,"showMaterialUpdate":false,"showSkybox":false,"showFlares":true,"showImageEffects":true,"showParticleSystems":true,"showVisualEffectGraphs":true,"m_FxEnabled":true},"in2DMode":false,"pivot":{"x":-17.4561710357666,"y":-12.267448425292969,"z":0.9902839660644531},"rotation":{"x":0.2162410020828247,"y":-0.6511898636817932,"z":0.20143069326877595,"w":0.6990412473678589},"size":12.043061256408692,"orthographic":false}